pinax/__init__.py
pinax/webanalytics/__init__.py
pinax/webanalytics/activity.py
pinax/webanalytics/apps.py
pinax/webanalytics/templates/pinax/webanalytics/_adwords_conversion.html
pinax/webanalytics/templates/pinax/webanalytics/_gauges.html
pinax/webanalytics/templates/pinax/webanalytics/_google.html
pinax/webanalytics/templates/pinax/webanalytics/_mixpanel.html
pinax/webanalytics/templatetags/__init__.py
pinax/webanalytics/templatetags/pinax_webanalytics_tags.py
pinax/webanalytics/tests/__init__.py
pinax/webanalytics/tests/models.py
pinax/webanalytics/tests/tests.py
pinax/webanalytics/tests/urls.py
pinax_webanalytics-5.0.0.dist-info/AUTHORS
pinax_webanalytics-5.0.0.dist-info/LICENSE
pinax_webanalytics-5.0.0.dist-info/METADATA
pinax_webanalytics-5.0.0.dist-info/WHEEL
pinax_webanalytics-5.0.0.dist-info/top_level.txt
pinax_webanalytics-5.0.0.dist-info/RECORD
